faciletoolkit/__init__.py
faciletoolkit/faciletoolkit.py
facile_toolkit-0.0.6.dist-info/LICENSE
facile_toolkit-0.0.6.dist-info/METADATA
facile_toolkit-0.0.6.dist-info/WHEEL
facile_toolkit-0.0.6.dist-info/top_level.txt
facile_toolkit-0.0.6.dist-info/RECORD
